SidraDataQualityApiPythonClient/__init__.py
SidraDataQualityApiPythonClient/api_client.py
SidraDataQualityApiPythonClient/configuration.py
SidraDataQualityApiPythonClient/rest.py
SidraDataQualityApiPythonClient/api/__init__.py
SidraDataQualityApiPythonClient/api/sidra_data_quality_api_s_management_dsu_api.py
SidraDataQualityApiPythonClient/api/sidra_data_quality_api_s_management_permission_api.py
SidraDataQualityApiPythonClient/api/sidra_data_quality_api_s_management_settings_api.py
SidraDataQualityApiPythonClient/api/sidra_data_quality_api_s_metadata_providers_api.py
SidraDataQualityApiPythonClient/api/sidra_data_quality_api_s_report_reports_api.py
SidraDataQualityApiPythonClient/api/sidra_data_quality_api_s_validation_check_processes_api.py
SidraDataQualityApiPythonClient/api/sidra_data_quality_api_s_validation_entity_deltas_api.py
SidraDataQualityApiPythonClient/api/sidra_data_quality_api_s_validation_expectations_api.py
SidraDataQualityApiPythonClient/api/sidra_data_quality_api_s_validation_report_api.py
SidraDataQualityApiPythonClient/api/sidra_data_quality_api_s_validation_results_api.py
SidraDataQualityApiPythonClient/api/sidra_data_quality_api_s_validation_suites_api.py
SidraDataQualityApiPythonClient/models/__init__.py
SidraDataQualityApiPythonClient/models/data_quality_api_controllers_management_models_dsu_dto.py
SidraDataQualityApiPythonClient/models/data_quality_api_controllers_metadata_models_asset_dto.py
SidraDataQualityApiPythonClient/models/data_quality_api_controllers_metadata_models_asset_response.py
SidraDataQualityApiPythonClient/models/data_quality_api_controllers_metadata_models_entity_dto.py
SidraDataQualityApiPythonClient/models/data_quality_api_controllers_report_models_report_dto.py
SidraDataQualityApiPythonClient/models/data_quality_api_controllers_validation_models_check_process_dto.py
SidraDataQualityApiPythonClient/models/data_quality_api_controllers_validation_models_expectation_dto.py
SidraDataQualityApiPythonClient-2025.1.0.dist-info/METADATA
SidraDataQualityApiPythonClient-2025.1.0.dist-info/WHEEL
SidraDataQualityApiPythonClient-2025.1.0.dist-info/top_level.txt
SidraDataQualityApiPythonClient-2025.1.0.dist-info/RECORD
