Metadata-Version: 2.1
Name: SidraDataQualityApiPythonClient
Version: 2025.1.0
Summary: DataQuality API
Home-page: UNKNOWN
Author-email: info@sidra.dev
License: UNKNOWN
Keywords: Swagger,DataQuality API
Platform: UNKNOWN
Requires-Dist: certifi
Requires-Dist: python-dateutil
Requires-Dist: six (>=1.10)
Requires-Dist: urllib3 (>=1.15)
